kshape/__init__.py
kshape/core.py
kshape/core_gpu.py
kshape-1.0.5.dist-info/LICENSE
kshape-1.0.5.dist-info/METADATA
kshape-1.0.5.dist-info/WHEEL
kshape-1.0.5.dist-info/top_level.txt
kshape-1.0.5.dist-info/zip-safe
kshape-1.0.5.dist-info/RECORD
